MANIFEST.in
setup.py
stathatasync.py
stathat_async.egg-info/PKG-INFO
stathat_async.egg-info/SOURCES.txt
stathat_async.egg-info/dependency_links.txt
stathat_async.egg-info/requires.txt
stathat_async.egg-info/top_level.txt