Metadata-Version: 1.0
Name: stathat-async
Version: 0.0.2
Summary: A simple multithreaded async API wrapper for StatHat.com
Home-page: https://github.com/j4mie/stathat-async
Author: Jamie Matthews
Author-email: jamie.matthews@gmail.com
License: MIT
Platform: UNKNOWN
